casepro.pods.dummy-0.2.1-py2.7-nspkg.pth
casepro/pods/dummy/__init__.py
casepro/pods/dummy/plugin.py
casepro.pods.dummy-0.2.1.dist-info/DESCRIPTION.rst
casepro.pods.dummy-0.2.1.dist-info/METADATA
casepro.pods.dummy-0.2.1.dist-info/RECORD
casepro.pods.dummy-0.2.1.dist-info/WHEEL
casepro.pods.dummy-0.2.1.dist-info/metadata.json
casepro.pods.dummy-0.2.1.dist-info/namespace_packages.txt
casepro.pods.dummy-0.2.1.dist-info/top_level.txt
