Metadata-Version: 2.0
Name: casepro.pods.dummy
Version: 0.2.1
Summary: Example casepro data pod returning statically configureddata
Home-page: http://github.com/praekelt/casepro.pods.dummy
Author: Praekelt Foundation
Author-email: dev@praekelt.com
License: BSD
Platform: UNKNOWN
Classifier: Programming Language :: Python
Classifier: Framework :: Django
Classifier: Topic :: Internet :: WWW/HTTP
Classifier: Topic :: Internet :: WWW/HTTP :: WSGI :: Application
